Workbook

Sheet Compras
B1: FAÇA O DOWNLOAD DO ARQUIVO PARA EDITAR
B3: 1- Você precisa preencher a fórmula somente nas células em amarelo e copia-la para as demais
B4: 2- Preencha a fórmula segundo o comentário feito na célula
B5: 3- Copie a sua fórmula para os demais estados e confira se ela está correta. (Pesquise sobre a função do "$" nas fórmulas em Excel) | AC5: Valor frete | AE5: 0.1
AC7: Total SP | AD7: =SUM(AC16:AC1453) -> 1.2669515e+08
AC8: Total MG | AD8: =SUM(AD16:AD1453) -> 1.2488674e+08
AC9: Total ES | AD9: =SUM(AE16:AE1453) -> 1.180031e+08
AC10: Total SC | AD10: =SUM(AF16:AF1453) -> 1.2420907e+08
AC11: Total RJ | AD11: =SUM(AG16:AG1453) -> 1.2708575e+08
AC12: Total PR | AD12: =SUM(AH16:AH1453) -> 1.2595177e+08
AC13: Total AM | AD13: =SUM(AI16:AI1453) -> 1.1846435e+08
H16: Chave auxiliar para pesquisa | O16: Kilômetros de frete com fábrica em | V16: Alíquota do imposto com fábrica em | AC16: Valor do bruto com Imposto e Frete
A17: SKU | B17: Descrição | C17: NCM | D17: OrigemMercadoria | E17: UF Origem | F17: Quantidade | G17: ValorLiquido | H17: SP | I17: MG | J17: ES | K17: SC | L17: RJ | M17: PR | N17: AM | O17: SP | P17: MG | Q17: ES | R17: SC | S17: RJ | T17: PR | U17: AM | V17: SP | W17: MG | X17: ES | Y17: SC | Z17: RJ | AA17: PR | AB17: AM | AC17: SP | AD17: MG | AE17: ES | AF17: SC | AG17: RJ | AH17: PR | AI17: AM
A18: 758517 | B18: CAMARAO.VIV.DESC.CONG 71 A 130 PUD 1 KG | C18: 03061790 | D18: NACIONAL | E18: BA | F18: 6070.6808 | G18: 163453.37 | H18: =$E18 & H$17 -> BASP | I18: =$E18 & I$17 -> BAMG | J18: =$E18 & J$17 -> BAES | K18: =$E18 & K$17 -> BASC | L18: =$E18 & L$17 -> BARJ | M18: =$E18 & M$17 -> BAPR | N18: =$E18 & N$17 -> BAAM | O18: =VLOOKUP(H18, KM!$A:$E, 5, 0) -> 1962 | P18: =VLOOKUP(I18, KM!$A:$E, 5, 0) -> 1372 | Q18: =VLOOKUP(J18, KM!$A:$E, 5, 0) -> 1202 | R18: =VLOOKUP(K18, KM!$A:$E, 5, 0) -> 2682 | S18: =VLOOKUP(L18, KM!$A:$E, 5, 0) -> 1649 | T18: =VLOOKUP(M18, KM!$A:$E, 5, 0) -> 2385 | U18: =VLOOKUP(N18, KM!$A:$E, 5, 0) -> 5009 | V18: =VLOOKUP(H18, IMPOSTO!$A:$D, 4, 0) -> 0.12 | W18: =VLOOKUP(I18, IMPOSTO!$A:$D, 4, 0) -> 0.12 | X18: =VLOOKUP(J18, IMPOSTO!$A:$D, 4, 0) -> 0.12 | Y18: =VLOOKUP(K18, IMPOSTO!$A:$D, 4, 0) -> 0.12 | Z18: =VLOOKUP(L18, IMPOSTO!$A:$D, 4, 0) -> 0.12 | AA18: =VLOOKUP(M18, IMPOSTO!$A:$D, 4, 0) -> 0.12 | AB18: =VLOOKUP(N18, IMPOSTO!$A:$D, 4, 0) -> 0.12 | AC18: =($G18 + O18 * $AE$5) / (1 - V18) -> 185965.42 | AD18: =($G18 + P18 * $AE$5) / (1 - W18) -> 185898.38 | AE18: =($G18 + Q18 * $AE$5) / (1 - X18) -> 185879.06 | AF18: =($G18 + R18 * $AE$5) / (1 - Y18) -> 186047.24 | AG18: =($G18 + S18 * $AE$5) / (1 - Z18) -> 185929.85 | AH18: =($G18 + T18 * $AE$5) / (1 - AA18) -> 186013.49 | AI18: =($G18 + U18 * $AE$5) / (1 - AB18) -> 186311.67
A19: 758675 | B19: CAMARAO AL MARE C/RABO 51/60 PEDTON 1 KG VIV.DESC.CONG | C19: 03061790 | D19: NACIONAL | E19: BA | F19: 5058.3638 | G19: 168132.14 | H19: =$E19 & H$17 -> BASP | I19: =$E19 & I$17 -> BAMG | J19: =$E19 & J$17 -> BAES | K19: =$E19 & K$17 -> BASC | L19: =$E19 & L$17 -> BARJ | M19: =$E19 & M$17 -> BAPR | N19: =$E19 & N$17 -> BAAM | O19: =VLOOKUP(H19, KM!$A:$E, 5, 0) -> 1962 | P19: =VLOOKUP(I19, KM!$A:$E, 5, 0) -> 1372 | Q19: =VLOOKUP(J19, KM!$A:$E, 5, 0) -> 1202 | R19: =VLOOKUP(K19, KM!$A:$E, 5, 0) -> 2682 | S19: =VLOOKUP(L19, KM!$A:$E, 5, 0) -> 1649 | T19: =VLOOKUP(M19, KM!$A:$E, 5, 0) -> 2385 | U19: =VLOOKUP(N19, KM!$A:$E, 5, 0) -> 5009 | V19: =VLOOKUP(H19, IMPOSTO!$A:$D, 4, 0) -> 0.12 | W19: =VLOOKUP(I19, IMPOSTO!$A:$D, 4, 0) -> 0.12 | X19: =VLOOKUP(J19, IMPOSTO!$A:$D, 4, 0) -> 0.12 | Y19: =VLOOKUP(K19, IMPOSTO!$A:$D, 4, 0) -> 0.12 | Z19: =VLOOKUP(L19, IMPOSTO!$A:$D, 4, 0) -> 0.12 | AA19: =VLOOKUP(M19, IMPOSTO!$A:$D, 4, 0) -> 0.12 | AB19: =VLOOKUP(N19, IMPOSTO!$A:$D, 4, 0) -> 0.12 | AC19: =($G19 + O19 * $AE$5) / (1 - V19) -> 191282.2 | AD19: =($G19 + P19 * $AE$5) / (1 - W19) -> 191215.16 | AE19: =($G19 + Q19 * $AE$5) / (1 - X19) -> 191195.84 | AF19: =($G19 + R19 * $AE$5) / (1 - Y19) -> 191364.02 | AG19: =($G19 + S19 * $AE$5) / (1 - Z19) -> 191246.63 | AH19: =($G19 + T19 * $AE$5) / (1 - AA19) -> 191330.27 | AI19: =($G19 + U19 * $AE$5) / (1 - AB19) -> 191628.45
A20: 790348 | B20: CAMARAO AL MARE C/RABO 41/50 PEDTON 1 KG VIV.DESC.CONG | C20: 03061790 | D20: NACIONAL | E20: BA | F20: 3152.5155 | G20: 111565.45 | H20: =$E20 & H$17 -> BASP | I20: =$E20 & I$17 -> BAMG | J20: =$E20 & J$17 -> BAES | K20: =$E20 & K$17 -> BASC | L20: =$E20 & L$17 -> BARJ | M20: =$E20 & M$17 -> BAPR | N20: =$E20 & N$17 -> BAAM | O20: =VLOOKUP(H20, KM!$A:$E, 5, 0) -> 1962 | P20: =VLOOKUP(I20, KM!$A:$E, 5, 0) -> 1372 | Q20: =VLOOKUP(J20, KM!$A:$E, 5, 0) -> 1202 | R20: =VLOOKUP(K20, KM!$A:$E, 5, 0) -> 2682 | S20: =VLOOKUP(L20, KM!$A:$E, 5, 0) -> 1649 | T20: =VLOOKUP(M20, KM!$A:$E, 5, 0) -> 2385 | U20: =VLOOKUP(N20, KM!$A:$E, 5, 0) -> 5009 | V20: =VLOOKUP(H20, IMPOSTO!$A:$D, 4, 0) -> 0.12 | W20: =VLOOKUP(I20, IMPOSTO!$A:$D, 4, 0) -> 0.12 | X20: =VLOOKUP(J20, IMPOSTO!$A:$D, 4, 0) -> 0.12 | Y20: =VLOOKUP(K20, IMPOSTO!$A:$D, 4, 0) -> 0.12 | Z20: =VLOOKUP(L20, IMPOSTO!$A:$D, 4, 0) -> 0.12 | AA20: =VLOOKUP(M20, IMPOSTO!$A:$D, 4, 0) -> 0.12 | AB20: =VLOOKUP(N20, IMPOSTO!$A:$D, 4, 0) -> 0.12 | AC20: =($G20 + O20 * $AE$5) / (1 - V20) -> 127001.87 | AD20: =($G20 + P20 * $AE$5) / (1 - W20) -> 126934.83 | AE20: =($G20 + Q20 * $AE$5) / (1 - X20) -> 126915.51 | AF20: =($G20 + R20 * $AE$5) / (1 - Y20) -> 127083.69 | AG20: =($G20 + S20 * $AE$5) / (1 - Z20) -> 126966.31 | AH20: =($G20 + T20 * $AE$5) / (1 - AA20) -> 127049.94 | AI20: =($G20 + U20 * $AE$5) / (1 - AB20) -> 127348.12
A21: 790348 | B21: CAMARAO AL MARE C/RABO 41/50 PEDTON 1 KG VIV.DESC.CONG | C21: 03061790 | D21: NACIONAL | E21: BA | F21: 1.261637 | G21: 44.648504 | H21: =$E21 & H$17 -> BASP | I21: =$E21 & I$17 -> BAMG | J21: =$E21 & J$17 -> BAES | K21: =$E21 & K$17 -> BASC | L21: =$E21 & L$17 -> BARJ | M21: =$E21 & M$17 -> BAPR | N21: =$E21 & N$17 -> BAAM | O21: =VLOOKUP(H21, KM!$A:$E, 5, 0) -> 1962 | P21: =VLOOKUP(I21, KM!$A:$E, 5, 0) -> 1372 | Q21: =VLOOKUP(J21, KM!$A:$E, 5, 0) -> 1202 | R21: =VLOOKUP(K21, KM!$A:$E, 5, 0) -> 2682 | S21: =VLOOKUP(L21, KM!$A:$E, 5, 0) -> 1649 | T21: =VLOOKUP(M21, KM!$A:$E, 5, 0) -> 2385 | U21: =VLOOKUP(N21, KM!$A:$E, 5, 0) -> 5009 | V21: =VLOOKUP(H21, IMPOSTO!$A:$D, 4, 0) -> 0.12 | W21: =VLOOKUP(I21, IMPOSTO!$A:$D, 4, 0) -> 0.12 | X21: =VLOOKUP(J21, IMPOSTO!$A:$D, 4, 0) -> 0.12 | Y21: =VLOOKUP(K21, IMPOSTO!$A:$D, 4, 0) -> 0.12 | Z21: =VLOOKUP(L21, IMPOSTO!$A:$D, 4, 0) -> 0.12 | AA21: =VLOOKUP(M21, IMPOSTO!$A:$D, 4, 0) -> 0.12 | AB21: =VLOOKUP(N21, IMPOSTO!$A:$D, 4, 0) -> 0.12 | AC21: =($G21 + O21 * $AE$5) / (1 - V21) -> 273.69148 | AD21: =($G21 + P21 * $AE$5) / (1 - W21) -> 206.64603 | AE21: =($G21 + Q21 * $AE$5) / (1 - X21) -> 187.32785 | AF21: =($G21 + R21 * $AE$5) / (1 - Y21) -> 355.50966 | AG21: =($G21 + S21 * $AE$5) / (1 - Z21) -> 238.1233 | AH21: =($G21 + T21 * $AE$5) / (1 - AA21) -> 321.75966 | AI21: =($G21 + U21 * $AE$5) / (1 - AB21) -> 619.94148
A22: 758517 | B22: CAMARAO.VIV.DESC.CONG 71 A 130 PUD 1 KG | C22: 03061790 | D22: NACIONAL | E22: BA | F22: 4181.0062 | G22: 110935.15 | H22: =$E22 & H$17 -> BASP | I22: =$E22 & I$17 -> BAMG | J22: =$E22 & J$17 -> BAES | K22: =$E22 & K$17 -> BASC | L22: =$E22 & L$17 -> BARJ | M22: =$E22 & M$17 -> BAPR | N22: =$E22 & N$17 -> BAAM | O22: =VLOOKUP(H22, KM!$A:$E, 5, 0) -> 1962 | P22: =VLOOKUP(I22, KM!$A:$E, 5, 0) -> 1372 | Q22: =VLOOKUP(J22, KM!$A:$E, 5, 0) -> 1202 | R22: =VLOOKUP(K22, KM!$A:$E, 5, 0) -> 2682 | S22: =VLOOKUP(L22, KM!$A:$E, 5, 0) -> 1649 | T22: =VLOOKUP(M22, KM!$A:$E, 5, 0) -> 2385 | U22: =VLOOKUP(N22, KM!$A:$E, 5, 0) -> 5009 | V22: =VLOOKUP(H22, IMPOSTO!$A:$D, 4, 0) -> 0.12 | W22: =VLOOKUP(I22, IMPOSTO!$A:$D, 4, 0) -> 0.12 | X22: =VLOOKUP(J22, IMPOSTO!$A:$D, 4, 0) -> 0.12 | Y22: =VLOOKUP(K22, IMPOSTO!$A:$D, 4, 0) -> 0.12 | Z22: =VLOOKUP(L22, IMPOSTO!$A:$D, 4, 0) -> 0.12 | AA22: =VLOOKUP(M22, IMPOSTO!$A:$D, 4, 0) -> 0.12 | AB22: =VLOOKUP(N22, IMPOSTO!$A:$D, 4, 0) -> 0.12 | AC22: =($G22 + O22 * $AE$5) / (1 - V22) -> 126285.63 | AD22: =($G22 + P22 * $AE$5) / (1 - W22) -> 126218.58 | AE22: =($G22 + Q22 * $AE$5) / (1 - X22) -> 126199.26 | AF22: =($G22 + R22 * $AE$5) / (1 - Y22) -> 126367.45 | AG22: =($G22 + S22 * $AE$5) / (1 - Z22) -> 126250.06 | AH22: =($G22 + T22 * $AE$5) / (1 - AA22) -> 126333.7 | AI22: =($G22 + U22 * $AE$5) / (1 - AB22) -> 126631.88
A23: 758517 | B23: CAMARAO.VIV.DESC.CONG 71 A 130 PUD 1 KG | C23: 03061790 | D23: NACIONAL | E23: BA | F23: 6868.7959 | G23: 189744.5 | H23: =$E23 & H$17 -> BASP | I23: =$E23 & I$17 -> BAMG | J23: =$E23 & J$17 -> BAES | K23: =$E23 & K$17 -> BASC | L23: =$E23 & L$17 -> BARJ | M23: =$E23 & M$17 -> BAPR | N23: =$E23 & N$17 -> BAAM | O23: =VLOOKUP(H23, KM!$A:$E, 5, 0) -> 1962 | P23: =VLOOKUP(I23, KM!$A:$E, 5, 0) -> 1372 | Q23: =VLOOKUP(J23, KM!$A:$E, 5, 0) -> 1202 | R23: =VLOOKUP(K23, KM!$A:$E, 5, 0) -> 2682 | S23: =VLOOKUP(L23, KM!$A:$E, 5, 0) -> 1649 | T23: =VLOOKUP(M23, KM!$A:$E, 5, 0) -> 2385 | U23: =VLOOKUP(N23, KM!$A:$E, 5, 0) -> 5009 | V23: =VLOOKUP(H23, IMPOSTO!$A:$D, 4, 0) -> 0.12 | W23: =VLOOKUP(I23, IMPOSTO!$A:$D, 4, 0) -> 0.12 | X23: =VLOOKUP(J23, IMPOSTO!$A:$D, 4, 0) -> 0.12 | Y23: =VLOOKUP(K23, IMPOSTO!$A:$D, 4, 0) -> 0.12 | Z23: =VLOOKUP(L23, IMPOSTO!$A:$D, 4, 0) -> 0.12 | AA23: =VLOOKUP(M23, IMPOSTO!$A:$D, 4, 0) -> 0.12 | AB23: =VLOOKUP(N23, IMPOSTO!$A:$D, 4, 0) -> 0.12 | AC23: =($G23 + O23 * $AE$5) / (1 - V23) -> 215841.7 | AD23: =($G23 + P23 * $AE$5) / (1 - W23) -> 215774.66 | AE23: =($G23 + Q23 * $AE$5) / (1 - X23) -> 215755.34 | AF23: =($G23 + R23 * $AE$5) / (1 - Y23) -> 215923.52 | AG23: =($G23 + S23 * $AE$5) / (1 - Z23) -> 215806.13 | AH23: =($G23 + T23 * $AE$5) / (1 - AA23) -> 215889.77 | AI23: =($G23 + U23 * $AE$5) / (1 - AB23) -> 216187.95
A24: 790348 | B24: CAMARAO AL MARE C/RABO 41/50 PEDTON 1 KG VIV.DESC.CONG | C24: 03061790 | D24: NACIONAL | E24: BA | F24: 2222.6368 | G24: 77710.925 | H24: =$E24 & H$17 -> BASP | I24: =$E24 & I$17 -> BAMG | J24: =$E24 & J$17 -> BAES | K24: =$E24 & K$17 -> BASC | L24: =$E24 & L$17 -> BARJ | M24: =$E24 & M$17 -> BAPR | N24: =$E24 & N$17 -> BAAM | O24: =VLOOKUP(H24, KM!$A:$E, 5, 0) -> 1962 | P24: =VLOOKUP(I24, KM!$A:$E, 5, 0) -> 1372 | Q24: =VLOOKUP(J24, KM!$A:$E, 5, 0) -> 1202 | R24: =VLOOKUP(K24, KM!$A:$E, 5, 0) -> 2682 | S24: =VLOOKUP(L24, KM!$A:$E, 5, 0) -> 1649 | T24: =VLOOKUP(M24, KM!$A:$E, 5, 0) -> 2385 | U24: =VLOOKUP(N24, KM!$A:$E, 5, 0) -> 5009 | V24: =VLOOKUP(H24, IMPOSTO!$A:$D, 4, 0) -> 0.12 | W24: =VLOOKUP(I24, IMPOSTO!$A:$D, 4, 0) -> 0.12 | X24: =VLOOKUP(J24, IMPOSTO!$A:$D, 4, 0) -> 0.12 | Y24: =VLOOKUP(K24, IMPOSTO!$A:$D, 4, 0) -> 0.12 | Z24: =VLOOKUP(L24, IMPOSTO!$A:$D, 4, 0) -> 0.12 | AA24: =VLOOKUP(M24, IMPOSTO!$A:$D, 4, 0) -> 0.12 | AB24: =VLOOKUP(N24, IMPOSTO!$A:$D, 4, 0) -> 0.12 | AC24: =($G24 + O24 * $AE$5) / (1 - V24) -> 88530.824 | AD24: =($G24 + P24 * $AE$5) / (1 - W24) -> 88463.778 | AE24: =($G24 + Q24 * $AE$5) / (1 - X24) -> 88444.46 | AF24: =($G24 + R24 * $AE$5) / (1 - Y24) -> 88612.642 | AG24: =($G24 + S24 * $AE$5) / (1 - Z24) -> 88495.255 | AH24: =($G24 + T24 * $AE$5) / (1 - AA24) -> 88578.892 | AI24: =($G24 + U24 * $AE$5) / (1 - AB24) -> 88877.074
A25: 790348 | B25: CAMARAO AL MARE C/RABO 41/50 PEDTON 1 KG VIV.DESC.CONG | C25: 03061790 | D25: NACIONAL | E25: BA | F25: 20942.682 | G25: 739757.6 | H25: =$E25 & H$17 -> BASP | I25: =$E25 & I$17 -> BAMG | J25: =$E25 & J$17 -> BAES | K25: =$E25 & K$17 -> BASC | L25: =$E25 & L$17 -> BARJ | M25: =$E25 & M$17 -> BAPR | N25: =$E25 & N$17 -> BAAM | O25: =VLOOKUP(H25, KM!$A:$E, 5, 0) -> 1962 | P25: =VLOOKUP(I25, KM!$A:$E, 5, 0) -> 1372 | Q25: =VLOOKUP(J25, KM!$A:$E, 5, 0) -> 1202 | R25: =VLOOKUP(K25, KM!$A:$E, 5, 0) -> 2682 | S25: =VLOOKUP(L25, KM!$A:$E, 5, 0) -> 1649 | T25: =VLOOKUP(M25, KM!$A:$E, 5, 0) -> 2385 | U25: =VLOOKUP(N25, KM!$A:$E, 5, 0) -> 5009 | V25: =VLOOKUP(H25, IMPOSTO!$A:$D, 4, 0) -> 0.12 | W25: =VLOOKUP(I25, IMPOSTO!$A:$D, 4, 0) -> 0.12 | X25: =VLOOKUP(J25, IMPOSTO!$A:$D, 4, 0) -> 0.12 | Y25: =VLOOKUP(K25, IMPOSTO!$A:$D, 4, 0) -> 0.12 | Z25: =VLOOKUP(L25, IMPOSTO!$A:$D, 4, 0) -> 0.12 | AA25: =VLOOKUP(M25, IMPOSTO!$A:$D, 4, 0) -> 0.12 | AB25: =VLOOKUP(N25, IMPOSTO!$A:$D, 4, 0) -> 0.12 | AC25: =($G25 + O25 * $AE$5) / (1 - V25) -> 840856.59 | AD25: =($G25 + P25 * $AE$5) / (1 - W25) -> 840789.54 | AE25: =($G25 + Q25 * $AE$5) / (1 - X25) -> 840770.22 | AF25: =($G25 + R25 * $AE$5) / (1 - Y25) -> 840938.41 | AG25: =($G25 + S25 * $AE$5) / (1 - Z25) -> 840821.02 | AH25: =($G25 + T25 * $AE$5) / (1 - AA25) -> 840904.66 | AI25: =($G25 + U25 * $AE$5) / (1 - AB25) -> 841202.84
A26: 790348 | B26: CAMARAO AL MARE C/RABO 41/50 PEDTON 1 KG VIV.DESC.CONG | C26: 03061790 | D26: NACIONAL | E26: BA | F26: 0.22237487 | G26: 7.77498 | H26: =$E26 & H$17 -> BASP | I26: =$E26 & I$17 -> BAMG | J26: =$E26 & J$17 -> BAES | K26: =$E26 & K$17 -> BASC | L26: =$E26 & L$17 -> BARJ | M26: =$E26 & M$17 -> BAPR | N26: =$E26 & N$17 -> BAAM | O26: =VLOOKUP(H26, KM!$A:$E, 5, 0) -> 1962 | P26: =VLOOKUP(I26, KM!$A:$E, 5, 0) -> 1372 | Q26: =VLOOKUP(J26, KM!$A:$E, 5, 0) -> 1202 | R26: =VLOOKUP(K26, KM!$A:$E, 5, 0) -> 2682 | S26: =VLOOKUP(L26, KM!$A:$E, 5, 0) -> 1649 | T26: =VLOOKUP(M26, KM!$A:$E, 5, 0) -> 2385 | U26: =VLOOKUP(N26, KM!$A:$E, 5, 0) -> 5009 | V26: =VLOOKUP(H26, IMPOSTO!$A:$D, 4, 0) -> 0.12 | W26: =VLOOKUP(I26, IMPOSTO!$A:$D, 4, 0) -> 0.12 | X26: =VLOOKUP(J26, IMPOSTO!$A:$D, 4, 0) -> 0.12 | Y26: =VLOOKUP(K26, IMPOSTO!$A:$D, 4, 0) -> 0.12 | Z26: =VLOOKUP(L26, IMPOSTO!$A:$D, 4, 0) -> 0.12 | AA26: =VLOOKUP(M26, IMPOSTO!$A:$D, 4, 0) -> 0.12 | AB26: =VLOOKUP(N26, IMPOSTO!$A:$D, 4, 0) -> 0.12 | AC26: =($G26 + O26 * $AE$5) / (1 - V26) -> 231.78975 | AD26: =($G26 + P26 * $AE$5) / (1 - W26) -> 164.7443 | AE26: =($G26 + Q26 * $AE$5) / (1 - X26) -> 145.42611 | AF26: =($G26 + R26 * $AE$5) / (1 - Y26) -> 313.60793 | AG26: =($G26 + S26 * $AE$5) / (1 - Z26) -> 196.22157 | AH26: =($G26 + T26 * $AE$5) / (1 - AA26) -> 279.85793 | AI26: =($G26 + U26 * $AE$5) / (1 - AB26) -> 578.03975
A27: 758517 | B27: CAMARAO.VIV.DESC.CONG 71 A 130 PUD 1 KG | C27: 03061790 | D27: NACIONAL | E27: BA | F27: 2871.2679 | G27: 76183.705 | H27: =$E27 & H$17 -> BASP | I27: =$E27 & I$17 -> BAMG | J27: =$E27 & J$17 -> BAES | K27: =$E27 & K$17 -> BASC | L27: =$E27 & L$17 -> BARJ | M27: =$E27 & M$17 -> BAPR | N27: =$E27 & N$17 -> BAAM | O27: =VLOOKUP(H27, KM!$A:$E, 5, 0) -> 1962 | P27: =VLOOKUP(I27, KM!$A:$E, 5, 0) -> 1372 | Q27: =VLOOKUP(J27, KM!$A:$E, 5, 0) -> 1202 | R27: =VLOOKUP(K27, KM!$A:$E, 5, 0) -> 2682 | S27: =VLOOKUP(L27, KM!$A:$E, 5, 0) -> 1649 | T27: =VLOOKUP(M27, KM!$A:$E, 5, 0) -> 2385 | U27: =VLOOKUP(N27, KM!$A:$E, 5, 0) -> 5009 | V27: =VLOOKUP(H27, IMPOSTO!$A:$D, 4, 0) -> 0.12 | W27: =VLOOKUP(I27, IMPOSTO!$A:$D, 4, 0) -> 0.12 | X27: =VLOOKUP(J27, IMPOSTO!$A:$D, 4, 0) -> 0.12 | Y27: =VLOOKUP(K27, IMPOSTO!$A:$D, 4, 0) -> 0.12 | Z27: =VLOOKUP(L27, IMPOSTO!$A:$D, 4, 0) -> 0.12 | AA27: =VLOOKUP(M27, IMPOSTO!$A:$D, 4, 0) -> 0.12 | AB27: =VLOOKUP(N27, IMPOSTO!$A:$D, 4, 0) -> 0.12 | AC27: =($G27 + O27 * $AE$5) / (1 - V27) -> 86795.346 | AD27: =($G27 + P27 * $AE$5) / (1 - W27) -> 86728.301 | AE27: =($G27 + Q27 * $AE$5) / (1 - X27) -> 86708.983 | AF27: =($G27 + R27 * $AE$5) / (1 - Y27) -> 86877.165 | AG27: =($G27 + S27 * $AE$5) / (1 - Z27) -> 86759.778 | AH27: =($G27 + T27 * $AE$5) / (1 - AA27) -> 86843.415 | AI27: =($G27 + U27 * $AE$5) / (1 - AB27) -> 87141.596
A28: 758517 | B28: CAMARAO.VIV.DESC.CONG 71 A 130 PUD 1 KG | C28: 03061790 | D28: NACIONAL | E28: BA | F28: 4717.083 | G28: 130305.3 | H28: =$E28 & H$17 -> BASP | I28: =$E28 & I$17 -> BAMG | J28: =$E28 & J$17 -> BAES | K28: =$E28 & K$17 -> BASC | L28: =$E28 & L$17 -> BARJ | M28: =$E28 & M$17 -> BAPR | N28: =$E28 & N$17 -> BAAM | O28: =VLOOKUP(H28, KM!$A:$E, 5, 0) -> 1962 | P28: =VLOOKUP(I28, KM!$A:$E, 5, 0) -> 1372 | Q28: =VLOOKUP(J28, KM!$A:$E, 5, 0) -> 1202 | R28: =VLOOKUP(K28, KM!$A:$E, 5, 0) -> 2682 | S28: =VLOOKUP(L28, KM!$A:$E, 5, 0) -> 1649 | T28: =VLOOKUP(M28, KM!$A:$E, 5, 0) -> 2385 | U28: =VLOOKUP(N28, KM!$A:$E, 5, 0) -> 5009 | V28: =VLOOKUP(H28, IMPOSTO!$A:$D, 4, 0) -> 0.12 | W28: =VLOOKUP(I28, IMPOSTO!$A:$D, 4, 0) -> 0.12 | X28: =VLOOKUP(J28, IMPOSTO!$A:$D, 4, 0) -> 0.12 | Y28: =VLOOKUP(K28, IMPOSTO!$A:$D, 4, 0) -> 0.12 | Z28: =VLOOKUP(L28, IMPOSTO!$A:$D, 4, 0) -> 0.12 | AA28: =VLOOKUP(M28, IMPOSTO!$A:$D, 4, 0) -> 0.12 | AB28: =VLOOKUP(N28, IMPOSTO!$A:$D, 4, 0) -> 0.12 | AC28: =($G28 + O28 * $AE$5) / (1 - V28) -> 148297.16 | AD28: =($G28 + P28 * $AE$5) / (1 - W28) -> 148230.12 | AE28: =($G28 + Q28 * $AE$5) / (1 - X28) -> 148210.8 | AF28: =($G28 + R28 * $AE$5) / (1 - Y28) -> 148378.98 | AG28: =($G28 + S28 * $AE$5) / (1 - Z28) -> 148261.6 | AH28: =($G28 + T28 * $AE$5) / (1 - AA28) -> 148345.23 | AI28: =($G28 + U28 * $AE$5) / (1 - AB28) -> 148643.41
A29: 758675 | B29: CAMARAO AL MARE C/RABO 51/60 PEDTON 1 KG VIV.DESC.CONG | C29: 03061790 | D29: NACIONAL | E29: BA | F29: 6470.888 | G29: 231732.23 | H29: =$E29 & H$17 -> BASP | I29: =$E29 & I$17 -> BAMG | J29: =$E29 & J$17 -> BAES | K29: =$E29 & K$17 -> BASC | L29: =$E29 & L$17 -> BARJ | M29: =$E29 & M$17 -> BAPR | N29: =$E29 & N$17 -> BAAM | O29: =VLOOKUP(H29, KM!$A:$E, 5, 0) -> 1962 | P29: =VLOOKUP(I29, KM!$A:$E, 5, 0) -> 1372 | Q29: =VLOOKUP(J29, KM!$A:$E, 5, 0) -> 1202 | R29: =VLOOKUP(K29, KM!$A:$E, 5, 0) -> 2682 | S29: =VLOOKUP(L29, KM!$A:$E, 5, 0) -> 1649 | T29: =VLOOKUP(M29, KM!$A:$E, 5, 0) -> 2385 | U29: =VLOOKUP(N29, KM!$A:$E, 5, 0) -> 5009 | V29: =VLOOKUP(H29, IMPOSTO!$A:$D, 4, 0) -> 0.12 | W29: =VLOOKUP(I29, IMPOSTO!$A:$D, 4, 0) -> 0.12 | X29: =VLOOKUP(J29, IMPOSTO!$A:$D, 4, 0) -> 0.12 | Y29: =VLOOKUP(K29, IMPOSTO!$A:$D, 4, 0) -> 0.12 | Z29: =VLOOKUP(L29, IMPOSTO!$A:$D, 4, 0) -> 0.12 | AA29: =VLOOKUP(M29, IMPOSTO!$A:$D, 4, 0) -> 0.12 | AB29: =VLOOKUP(N29, IMPOSTO!$A:$D, 4, 0) -> 0.12 | AC29: =($G29 + O29 * $AE$5) / (1 - V29) -> 263555.04 | AD29: =($G29 + P29 * $AE$5) / (1 - W29) -> 263487.99 | AE29: =($G29 + Q29 * $AE$5) / (1 - X29) -> 263468.68 | AF29: =($G29 + R29 * $AE$5) / (1 - Y29) -> 263636.86 | AG29: =($G29 + S29 * $AE$5) / (1 - Z29) -> 263519.47 | AH29: =($G29 + T29 * $AE$5) / (1 - AA29) -> 263603.11 | AI29: =($G29 + U29 * $AE$5) / (1 - AB29) -> 263901.29
... A1453: 790350 | B1453: CLIP HASHI PCT 500 UNID | C1453: 39235000 | D1453: NACIONAL | E1453: SP | F1453: 50.796813 | G1453: 5070.7918 | H1453: =$E1453 & H$17 -> SPSP | I1453: =$E1453 & I$17 -> SPMG | J1453: =$E1453 & J$17 -> SPES | K1453: =$E1453 & K$17 -> SPSC | L1453: =$E1453 & L$17 -> SPRJ | M1453: =$E1453 & M$17 -> SPPR | N1453: =$E1453 & N$17 -> SPAM | O1453: =VLOOKUP(H1453, KM!$A:$E, 5, 0) -> 0 | P1453: =VLOOKUP(I1453, KM!$A:$E, 5, 0) -> 586 | Q1453: =VLOOKUP(J1453, KM!$A:$E, 5, 0) -> 882 | R1453: =VLOOKUP(K1453, KM!$A:$E, 5, 0) -> 705 | S1453: =VLOOKUP(L1453, KM!$A:$E, 5, 0) -> 429 | T1453: =VLOOKUP(M1453, KM!$A:$E, 5, 0) -> 408 | U1453: =VLOOKUP(N1453, KM!$A:$E, 5, 0) -> 3971 | V1453: =VLOOKUP(H1453, IMPOSTO!$A:$D, 4, 0) -> 0.18 | W1453: =VLOOKUP(I1453, IMPOSTO!$A:$D, 4, 0) -> 0.12 | X1453: =VLOOKUP(J1453, IMPOSTO!$A:$D, 4, 0) -> 0.07 | Y1453: =VLOOKUP(K1453, IMPOSTO!$A:$D, 4, 0) -> 0.12 | Z1453: =VLOOKUP(L1453, IMPOSTO!$A:$D, 4, 0) -> 0.12 | AA1453: =VLOOKUP(M1453, IMPOSTO!$A:$D, 4, 0) -> 0.12 | AB1453: =VLOOKUP(N1453, IMPOSTO!$A:$D, 4, 0) -> 0.07 | AC1453: =($G1453 + O1453 * $AE$5) / (1 - V1453) -> 6183.8925 | AD1453: =($G1453 + P1453 * $AE$5) / (1 - W1453) -> 5828.8544 | AE1453: =($G1453 + Q1453 * $AE$5) / (1 - X1453) -> 5547.303 | AF1453: =($G1453 + R1453 * $AE$5) / (1 - Y1453) -> 5842.3771 | AG1453: =($G1453 + S1453 * $AE$5) / (1 - Z1453) -> 5811.0134 | AH1453: =($G1453 + T1453 * $AE$5) / (1 - AA1453) -> 5808.6271 | AI1453: =($G1453 + U1453 * $AE$5) / (1 - AB1453) -> 5879.4536

Sheet KM
A1: Chave | B1: De | C1: Para | D1: AUX | E1: KM
A2: =B2&C2 -> ACMT | B2: AC | C2: MT | D2: 13 | E2: 1990
A3: =B3&C3 -> ACMS | B3: AC | C3: MS | D3: 12 | E3: 2684
A4: =B4&C4 -> ACPA | B4: AC | C4: PA | D4: 14 | E4: 4931
A5: =B5&C5 -> ACPB | B5: AC | C5: PB | D5: 15 | E5: 5356
A6: =B6&C6 -> ACRN | B6: AC | C6: RN | D6: 20 | E6: 5533
A7: =B7&C7 -> ALAC | B7: AL | C7: AC | D7: 1 | E7: 5039
A8: =B8&C8 -> ALAL | B8: AL | C8: AL | D8: 2 | E8: 0
A9: =B9&C9 -> ALBA | B9: AL | C9: BA | D9: 5 | E9: 632
A10: =B10&C10 -> ALCE | B10: AL | C10: CE | D10: 6 | E10: 1075
A11: =B11&C11 -> ALMA | B11: AL | C11: MA | D11: 10 | E11: 1672
A12: =B12&C12 -> ALRS | B12: AL | C12: RS | D12: 23 | E12: 3572
A13: =B13&C13 -> APAC | B13: AP | C13: AC | D13: 1 | E13: 0
... A1372: =B1372&C1372 -> TOTO | B1372: TO | C1372: TO | D1372: 27 | E1372: 0

Sheet IMPOSTO
A1: Chave | B1: De | C1: Para | D1: Alíquota
A2: ACAC | B2: AC | C2: AC | D2: 0.18
A3: ACAL | B3: AC | C3: AL | D3: 0.12
A4: ACAP | B4: AC | C4: AP | D4: 0.12
A5: ACAM | B5: AC | C5: AM | D5: 0.12
A6: ACBA | B6: AC | C6: BA | D6: 0.12
A7: ACCE | B7: AC | C7: CE | D7: 0.12
A8: ACDF | B8: AC | C8: DF | D8: 0.12
A9: ACES | B9: AC | C9: ES | D9: 0.12
A10: ACGO | B10: AC | C10: GO | D10: 0.12
A11: ACMA | B11: AC | C11: MA | D11: 0.12
A12: ACMT | B12: AC | C12: MT | D12: 0.12
A13: ACMS | B13: AC | C13: MS | D13: 0.12
... A1459: TOTO | B1459: TO | C1459: TO | D1459: 0.18
